Metadata-Version: 1.1
Name: pymathlibs
Version: 2021.9.1.1
Summary: PyMathLibs is a free math library in python. This library contains most of the math class libs, and some other features.
Home-page: UNKNOWN
Author: NoobBit
Author-email: noobbit90@gmail.com
License: MIT
Keywords: math
Platform: UNKNOWN
Classifier: Development Status :: 5 - Production/Stable
Classifier: Intended Audience :: Education
Classifier: Operating System :: Microsoft :: Windows :: Windows 10
Classifier: License :: OSI Approved :: MIT License
Classifier: Programming Language :: Python :: 3
